statsWaveletFilt/__init__.py
statsWaveletFilt/cusum.py
statsWaveletFilt/filtration.py
statsWaveletFilt/miscellaneous.py
statsWaveletFilt/signals.py
statsWaveletFilt/threshold.py
statsWaveletFiltr/__init__.py
statsWaveletFiltr/cusum.py
statsWaveletFiltr/filtration.py
statsWaveletFiltr/miscellaneous.py
statsWaveletFiltr/signals.py
statsWaveletFiltr/threshold.py
statsWaveletFilt-0.0.4.dist-info/LICENSE
statsWaveletFilt-0.0.4.dist-info/METADATA
statsWaveletFilt-0.0.4.dist-info/WHEEL
statsWaveletFilt-0.0.4.dist-info/top_level.txt
statsWaveletFilt-0.0.4.dist-info/RECORD
