Metadata-Version: 2.1
Name: statsWaveletFilt
Version: 0.0.4
Summary: A statistical signal processing package
Home-page: https://github.com/Tiarles/Statistical-Wavelet-Filtering
Author: Tiarles Guterres
Author-email: tiarlesmoralles@hotmail.com
License: UNKNOWN
Project-URL: Documentation, https://statistical-wavelet-filtering.readthedocs.io/en/master/
Project-URL: Source, https://github.com/Tiarles/Statistical-Wavelet-Filtering
Platform: UNKNOWN
Classifier: Programming Language :: Python :: 3
Classifier: License :: OSI Approved :: MIT License
Classifier: Operating System :: OS Independent
